{
  "/_not-found": "app/_not-found.js",
  "/admin/biletler/page": "app/admin/biletler/page.js",
  "/admin/chat/page": "app/admin/chat/page.js",
  "/admin/livestream/page": "app/admin/livestream/page.js",
  "/admin/kod-yonetimi/page": "app/admin/kod-yonetimi/page.js",
  "/admin/homepage/page": "app/admin/homepage/page.js",
  "/admin/kazanclar/page": "app/admin/kazanclar/page.js",
  "/admin/page": "app/admin/page.js",
  "/admin/sponsorlar/debug/page": "app/admin/sponsorlar/debug/page.js",
  "/admin/roles/page": "app/admin/roles/page.js",
  "/admin/settings/page": "app/admin/settings/page.js",
  "/admin/sponsors/page": "app/admin/sponsors/page.js",
  "/admin/market/page": "app/admin/market/page.js",
  "/admin/transactions/page": "app/admin/transactions/page.js",
  "/admin/users/[userId]/awards/page": "app/admin/users/[userId]/awards/page.js",
  "/admin/sponsorlar/page": "app/admin/sponsorlar/page.js",
  "/admin/etkinlikler/page": "app/admin/etkinlikler/page.js",
  "/admin/users/[userId]/bonuses/page": "app/admin/users/[userId]/bonuses/page.js",
  "/admin/users/[userId]/partners/page": "app/admin/users/[userId]/partners/page.js",
  "/api/admin/make-admin/route": "app/api/admin/make-admin/route.js",
  "/admin/users/page": "app/admin/users/page.js",
  "/api/auth/forgot-password-v2/route": "app/api/auth/forgot-password-v2/route.js",
  "/api/auth/validate-token/route": "app/api/auth/validate-token/route.js",
  "/api/auth/login/route": "app/api/auth/login/route.js",
  "/api/market/items/image-refresh/route": "app/api/market/items/image-refresh/route.js",
  "/api/auth/register/route": "app/api/auth/register/route.js",
  "/api/transactions/bulk/route": "app/api/transactions/bulk/route.js",
  "/api/auth/reset-password-v2/route": "app/api/auth/reset-password-v2/route.js",
  "/api/transactions/route": "app/api/transactions/route.js",
  "/api/upload/route": "app/api/upload/route.js",
  "/biletler/page": "app/biletler/page.js",
  "/api/user/coins/route": "app/api/user/coins/route.js",
  "/cark-cevir/page": "app/cark-cevir/page.js",
  "/etkinlikler/page": "app/etkinlikler/page.js",
  "/forgot-password/page": "app/forgot-password/page.js",
  "/cevrim-etkinlikleri/page": "app/cevrim-etkinlikleri/page.js",
  "/chat/page": "app/chat/page.js",
  "/favicon.ico/route": "app/favicon.ico/route.js",
  "/haberler/page": "app/haberler/page.js",
  "/market/page": "app/market/page.js",
  "/profil/settings/page": "app/profil/settings/page.js",
  "/page": "app/page.js",
  "/profil/page": "app/profil/page.js",
  "/sizden-gelenler/page": "app/sizden-gelenler/page.js",
  "/sponsorlar/page": "app/sponsorlar/page.js",
  "/turnuvalar/page": "app/turnuvalar/page.js",
  "/user/partners/page": "app/user/partners/page.js",
  "/liderlik-tablosu/page": "app/liderlik-tablosu/page.js",
  "/admin/users/[userId]/page": "app/admin/users/[userId]/page.js",
  "/api/list-market-images/route": "app/api/list-market-images/route.js",
  "/api/market/items/delete/route": "app/api/market/items/delete/route.js",
  "/api/market/items/route": "app/api/market/items/route.js",
  "/api/upload/market-images/route": "app/api/upload/market-images/route.js",
  "/giris/page": "app/giris/page.js",
  "/reset-password/page": "app/reset-password/page.js",
  "/kayit/page": "app/kayit/page.js",
  "/sifre-sifirlama/[token]/page": "app/sifre-sifirlama/[token]/page.js",
  "/sifremi-unuttum/page": "app/sifremi-unuttum/page.js"
}